CIC.v
`timescale 10ps/10ps

module CIC #(parameter width = 31)
			(input wire               clk,
			input wire               rst,
			input wire        [15:0] decimation_ratio,
			input wire signed  d_in,
			output reg signed [30:0]  d_out,
			output reg 				 d_clk);

reg signed [width-1:0] d_tmp, d_d_tmp;

// Integrator stage registers

reg signed [width-1:0] d1;
reg signed [width-1:0] d2;
reg signed [width-1:0] d3;
reg signed [width-1:0] d4;
reg signed [width-1:0] d5;

// Comb stage registers

reg signed [width-1:0] d6, d_d6;
reg signed [width-1:0] d7, d_d7;
reg signed [width-1:0] d8, d_d8;
reg signed [width-1:0] d9, d_d9;
reg signed [width-1:0] d10;

reg [15:0] count;

reg v_comb;  // Valid signal for comb section running at output rate

reg d_clk_tmp;
 
	always @(posedge clk)
	begin
		if (rst)
		begin
			d1 <= 0;
			d2 <= 0;
			d3 <= 0;
			d4 <= 0;
			d5 <= 0;
			count <= 0;
		end else
		begin
			// Integrator section
			d1 <= d_in + d1;
			
			d2 <= d1 + d2;
			
			d3 <= d2 + d3;
			
			d4 <= d3 + d4;
			
			d5 <= d4 + d5;
			
			// Decimation
			
			if (count == decimation_ratio - 1)
			begin
				count <= 16'b0;
				d_tmp <= d5;
				d_clk_tmp <= 1'b1;
				v_comb <= 1'b1;
			end else if (count == decimation_ratio >> 1)
			begin
				d_clk_tmp <= 1'b0;
				count <= count + 16'd1;
				v_comb <= 1'b0;
			end else
			begin
				count <= count + 16'd1;
				v_comb <= 1'b0;
			end
		end
	end
	
	always @(posedge clk)  // Comb section running at output rate
	begin
		d_clk <= d_clk_tmp;
		if (rst)
		begin
			d6 <= 0;
			d7 <= 0;
			d8 <= 0;
			d9 <= 0;
			d10 <= 0;
			d_d6 <= 0;
			d_d7 <= 0;
			d_d8 <= 0;
			d_d9 <= 0;
			d_out <= 8'b0;
		end else
		begin
			if (v_comb)
			begin
				// Comb section
				d_d_tmp <= d_tmp;
				
				d6 <= d_tmp - d_d_tmp;
				d_d6 <= d6;

				d7 <= d6 - d_d6;
				d_d7 <= d7;

				d8 <= d7 - d_d7;
				d_d8 <= d8;

				d9 <= d8 - d_d8;
				d_d9 <= d9;

				d10 <= d9 - d_d9;
				
				d_out <= d10 >>> (width - 8);
			end
		end
	end								
endmodule

CIC_tb.v
`include "CIC.v"

`timescale 10ps/10ps

module CIC_tb;
	reg               clk;
	reg               rst;
	reg        [15:0] decimation_ratio;
	reg signed  d_in;
	wire signed [30:0]  d_out;
	wire 			   d_clk;
	
	integer x_in, x_read;
	
	CIC #(.width(18)) CIC(.clk(clk),
						   .rst(rst),
						   .decimation_ratio(decimation_ratio),
						   .d_in(d_in),
						   .d_out(d_out),
						   .d_clk(d_clk));
		   
	always #3125 clk = ~clk;
	
	initial
	begin
		clk <= 1'b0;
		rst <= 1'b0;
		decimation_ratio <= 16'd64;
		d_in <= 1'b0;
		x_in <= $fopen("bitstream.txt","r");
		$dumpfile("signals.vcd"); // Name of the signal dump file
    	$dumpvars(0, CIC_tb); // Signals to dump
	end 
	
	initial
	begin
		repeat(10) @(posedge clk);
		rst <= 1'b1;
		@(posedge clk);
		rst <= 1'b0;
		repeat(5) @(posedge clk);
		while (!$feof(x_in))
		begin
			x_read <= $fscanf(x_in,"%d\n",d_in);
			@(posedge clk);
		end
		repeat(16000) @(posedge clk);
		$fclose(x_in);
		$finish();
	end
endmodule

signals.vcd
$date
	Fri Nov  1 01:34:10 2024
$end
$version
	Icarus Verilog
$end
$timescale
	10ps
$end
$scope module CIC_tb $end
$var wire 31 ! d_out [30:0] $end
$var wire 1 " d_clk $end
$var reg 1 # clk $end
$var reg 1 $ d_in $end
$var reg 16 % decimation_ratio [15:0] $end
$var reg 1 & rst $end
$var integer 32 ' x_in [31:0] $end
$var integer 32 ( x_read [31:0] $end
$scope module CIC $end
$var wire 1 # clk $end
$var wire 1 $ d_in $end
$var wire 16 ) decimation_ratio [15:0] $end
$var wire 1 & rst $end
$var parameter 32 * width $end
$var reg 16 + count [15:0] $end
$var reg 18 , d1 [17:0] $end
$var reg 18 - d10 [17:0] $end
$var reg 18 . d2 [17:0] $end
$var reg 18 / d3 [17:0] $end
$var reg 18 0 d4 [17:0] $end
$var reg 18 1 d5 [17:0] $end
$var reg 18 2 d6 [17:0] $end
$var reg 18 3 d7 [17:0] $end
$var reg 18 4 d8 [17:0] $end
$var reg 18 5 d9 [17:0] $end
$var reg 1 " d_clk $end
$var reg 1 6 d_clk_tmp $end
$var reg 18 7 d_d6 [17:0] $end
$var reg 18 8 d_d7 [17:0] $end
$var reg 18 9 d_d8 [17:0] $end
$var reg 18 : d_d9 [17:0] $end
$var reg 18 ; d_d_tmp [17:0] $end
$var reg 31 < d_out [30:0] $end
$var reg 18 = d_tmp [17:0] $end
$var reg 1 > v_comb $end
$upscope $end
$upscope $end
$enddefinitions $end
$comment Show the parameter values. $end
$dumpall
b10010 *
$end
#0
$dumpvars
x>
bx =
bx <
bx ;
bx :
bx 9
bx 8
bx 7
x6
bx 5
bx 4
bx 3
bx 2
bx 1
bx 0
bx /
bx .
bx -
bx ,
bx +
b1000000 )
bx (
b10000000000000000000000000000011 '
0&
b1000000 %
0$
0#
x"
bx !
$end
#3125
0>
1#
#6250
0#
#9375
1#
#12500
0#
#15625
1#
#18750
0#
#21875
1#
#25000
0#
#28125
1#
#31250
0#
#34375
1#
#37500
0#
#40625
1#
#43750
0#
#46875
1#
#50000
0#
#53125
1#
#56250
0#
#59375
1&
1#
#62500
0#
#65625
b0 +
b0 1
b0 0
b0 /
b0 .
b0 ,
b0 !
b0 <
b0 :
b0 9
b0 8
b0 7
b0 -
b0 5
b0 4
b0 3
b0 2
0&
1#
#68750
0#
#71875
b1 +
1#
#75000
0#
#78125
b10 +
1#
#81250
0#
#84375
b11 +
1#
#87500
0#
#90625
b100 +
1#
#93750
0#
#96875
b1 (
b101 +
1$
1#
#100000
0#
#103125
b110 +
0$
1#
#106250
0#
#109375
b111 +
1#
#112500
0#
#115625
b1000 +
1#
#118750
0#
#121875
b1001 +
1$
1#
#125000
0#
#128125
b1010 +
0$
1#
#131250
0#
#134375
b1011 +
1#
#137500
0#
#140625
b1100 +
b111111111111111111 ,
1$
1#
#143750
0#
#146875
b1101 +
b111111111111111111 .
b111111111111111110 ,
0$
1#
#150000
0#
#153125
b1110 +
b111111111111111111 /
b111111111111111101 .
1#
#156250
0#
#159375
b1111 +
b111111111111111111 0
b111111111111111100 /
b111111111111111011 .
1$
1#
#162500
0#
#165625
b10000 +
b111111111111111111 1
b111111111111111011 0
b111111111111110111 /
b111111111111111001 .
0$
1#
#168750
0#
#171875
b10001 +
b111111111111111010 1
b111111111111110010 0
b111111111111110000 /
b111111111111110111 .
1#
#175000
0#
#178125
b10010 +
b111111111111101100 1
b111111111111100010 0
b111111111111100111 /
b111111111111110101 .
b111111111111111101 ,
1$
1#
#181250
0#
#184375
b10011 +
b111111111111001110 1
b111111111111001001 0
b111111111111011100 /
b111111111111110010 .
b111111111111111100 ,
0$
1#
#187500
0#
#190625
b10100 +
b111111111110010111 1
b111111111110100101 0
b111111111111001110 /
b111111111111101110 .
1#
#193750
0#
#196875
b10101 +
b111111111100111100 1
b111111111101110011 0
b111111111110111100 /
b111111111111101010 .
1$
1#
#200000
0#
#203125
b10110 +
b111111111010101111 1
b111111111100101111 0
b111111111110100110 /
b111111111111100110 .
0$
1#
#206250
0#
#209375
b10111 +
b111111110111011110 1
b111111111011010101 0
b111111111110001100 /
b111111111111100010 .
1$
1#
#212500
0#
#215625
b11000 +
b111111110010110011 1
b111111111001100001 0
b111111111101101110 /
b111111111111011110 .
0$
1#
#218750
0#
#221875
b11001 +
b111111101100010100 1
b111111110111001111 0
b111111111101001100 /
b111111111111011010 .
1#
#225000
0#
#228125
b11010 +
b111111100011100011 1
b111111110100011011 0
b111111111100100110 /
b111111111111010110 .
b111111111111111011 ,
1$
1#
#231250
0#
#234375
b11011 +
b111111010111111110 1
b111111110001000001 0
b111111111011111100 /
b111111111111010001 .
b111111111111111010 ,
0$
1#
#237500
0#
#240625
b11100 +
b111111001000111111 1
b111111101100111101 0
b111111111011001101 /
b111111111111001011 .
b111111111111111001 ,
1$
1#
#243750
0#
#246875
b11101 +
b111110110101111100 1
b111111101000001010 0
b111111111010011000 /
b111111111111000100 .
b111111111111111000 ,
0$
1#
#250000
0#
#253125
b11110 +
b111110011110000110 1
b111111100010100010 0
b111111111001011100 /
b111111111110111100 .
b111111111111110111 ,
1$
1#
#256250
0#
#259375
b11111 +
b111110000000101000 1
b111111011011111110 0
b111111111000011000 /
b111111111110110011 .
b111111111111110110 ,
0$
1#
#262500
0#
#265625
b100000 +
b111101011100100110 1
b111111010100010110 0
b111111110111001011 /
b111111111110101001 .
b111111111111110101 ,
1$
1#
#268750
0#
#271875
b100001 +
06
b111100110000111100 1
b111111001011100001 0
b111111110101110100 /
b111111111110011110 .
b111111111111110100 ,
0$
1#
#275000
0#
#278125
b100010 +
b111011111100011101 1
b111111000001010101 0
b111111110100010010 /
b111111111110010010 .
b111111111111110011 ,
0"
1$
1#
#281250
0#
#284375
b100011 +
b111010111101110010 1
b111110110101100111 0
b111111110010100100 /
b111111111110000101 .
b111111111111110010 ,
0$
1#
#287500
0#
#290625
b100100 +
b111001110011011001 1
b111110101000001011 0
b111111110000101001 /
b111111111101110111 .
b111111111111110001 ,
1$
1#
#293750
0#
#296875
b100101 +
b111000011011100100 1
b111110011000110100 0
b111111101110100000 /
b111111111101101000 .
b111111111111110000 ,
0$
1#
#300000
0#
#303125
b100110 +
b110110110100011000 1
b111110000111010100 0
b111111101100001000 /
b111111111101011000 .
b111111111111101111 ,
1$
1#
#306250
0#
#309375
b100111 +
b110100111011101100 1
b111101110011011100 0
b111111101001100000 /
b111111111101000111 .
b111111111111101110 ,
0$
1#
#312500
0#
#315625
b101000 +
b110010101111001000 1
b111101011100111100 0
b111111100110100111 /
b111111111100110101 .
1#
#318750
0#
#321875
b101001 +
b110000001100000100 1
b111101000011100011 0
b111111100011011100 /
b111111111100100011 .
1$
1#
#325000
0#
#328125
b101010 +
b101101001111100111 1
b111100100110111111 0
b111111011111111111 /
b111111111100010001 .
0$
1#
#331250
0#
#334375
b101011 +
b101001110110100110 1
b111100000110111110 0
b111111011100010000 /
b111111111011111111 .
1$
1#
#337500
0#
#340625
b101100 +
b100101111101100100 1
b111011100011001110 0
b111111011000001111 /
b111111111011101101 .
0$
1#
#343750
0#
#346875
b101101 +
b100001100000110010 1
b111010111011011101 0
b111111010011111100 /
b111111111011011011 .
1$
1#
#350000
0#
#353125
b101110 +
b11100011100001111 1
b111010001111011001 0
b111111001111010111 /
b111111111011001001 .
0$
1#
#356250
0#
#359375
b101111 +
b10110101011101000 1
b111001011110110000 0
b111111001010100000 /
b111111111010110111 .
1$
1#
#362500
0#
#365625
b110000 +
b10000001010011000 1
b111000101001010000 0
b111111000101010111 /
b111111111010100101 .
0$
1#
#368750
0#
#371875
b110001 +
b1000110011101000 1
b110111101110100111 0
b111110111111111100 /
b111111111010010011 .
1$
1#
#375000
0#
#378125
b110010 +
b100010001111 1
b110110101110100011 0
b111110111010001111 /
b111111111010000001 .
0$
1#
#381250
0#
#384375
b110011 +
b110111010000110010 1
b110101101000110010 0
b111110110100010000 /
b111111111001101111 .
1$
1#
#387500
0#
#390625
b110100 +
b101100111001100100 1
b110100011101000010 0
b111110101101111111 /
b111111111001011101 .
0$
1#
#393750
0#
#396875
b110101 +
b100001010110100110 1
b110011001011000001 0
b111110100111011100 /
b111111111001001011 .
1$
1#
#400000
0#
#403125
b110110 +
b10100100001100111 1
b110001110010011101 0
b111110100000100111 /
b111111111000111001 .
0$
1#
#406250
0#
#409375
b110111 +
b110010100000100 1
b110000010011000100 0
b111110011001100000 /
b111111111000100111 .
1$
1#
#412500
0#
#415625
b111000 +
b110110100111001000 1
b101110101100100100 0
b111110010010000111 /
b111111111000010101 .
0$
1#
#418750
0#
#421875
b111001 +
b100101010011101100 1
b101100111110101011 0
b111110001010011100 /
b111111111000000011 .
1$
1#
#425000
0#
#428125
b111010 +
b10010010010010111 1
b101011001001000111 0
b111110000010011111 /
b111111110111110001 .
0$
1#
#431250
0#
#434375
b111011 +
b111101011011011110 1
b101001001011100110 0
b111101111010010000 /
b111111110111011111 .
1$
1#
#437500
0#
#440625
b111100 +
b100110100111000100 1
b100111000101110110 0
b111101110001101111 /
b111111110111001101 .
0$
1#
#443750
0#
#446875
b111101 +
b1101101100111010 1
b100100110111100101 0
b111101101000111100 /
b111111110110111011 .
1$
1#
#450000
0#
#453125
b111110 +
b110010100100011111 1
b100010100000100001 0
b111101011111110111 /
b111111110110101001 .
0$
1#
#456250
0#
#459375
b111111 +
b10101000101000000 1
b100000000000011000 0
b111101010110100000 /
b111111110110010111 .
1$
1#
#462500
0#
#465625
1>
16
b10101000101000000 =
b0 +
b110101000101011000 1
b11101010110111000 0
b111101001100110111 /
b111111110110000101 .
0$
1#
#468750
0#
#471875
bx 2
b10101000101000000 ;
1"
0>
b1 +
b10010011100010000 1
b11010100011101111 0
b111101000010111100 /
b111111110101110011 .
1#
#475000
0#
#478125
b10 +
b101100111111111111 1
b10111100110101011 0
b111100111000101111 /
b111111110101100001 .
b111111111111101101 ,
1$
1#
#481250
0#
#484375
b11 +
b100100110101010 1
b10100011111011010 0
b111100101110010000 /
b111111110101001110 .
b111111111111101100 ,
0$
1#
#487500
0#
#490625
b100 +
b11001000110000100 1
b10001001101101010 0
b111100100011011110 /
b111111110100111010 .
b111111111111101011 ,
1$
1#
#493750
0#
#496875
b101 +
b101010010011101110 1
b1101110001001000 0
b111100011000011000 /
b111111110100100101 .
b111111111111101010 ,
0$
1#
#500000
0#
#503125
b110 +
b111000000100110110 1
b1010001001100000 0
b111100001100111101 /
b111111110100001111 .
1#
#506250
0#
#509375
b111 +
b10001110010110 1
b110010110011101 0
b111100000001001100 /
b111111110011111001 .
1$
1#
#512500
0#
#515625
b1000 +
b1000100100110011 1
b10010111101001 0
b111011110101000101 /
b111111110011100011 .
0$
1#
#518750
0#
#521875
b1001 +
b1010111100011100 1
b111110001100101110 0
b111011101000101000 /
b111111110011001101 .
1$
1#
#525000
0#
#528125
b1010 +
b1001001001001010 1
b111001110101010110 0
b111011011011110101 /
b111111110010110111 .
0$
1#
#531250
0#
#534375
b1011 +
b10111110100000 1
b110101010001001011 0
b111011001110101100 /
b111111110010100001 .
1#
#537500
0#
#540625
b1100 +
b111000001111101011 1
b110000011111110111 0
b111011000001001101 /
b111111110010001011 .
b111111111111101001 ,
1$
1#
#543750
0#
#546875
b1101 +
b101000101111100010 1
b101011100001000100 0
b111010110011011000 /
b111111110001110100 .
b111111111111101000 ,
0$
1#
#550000
0#
#553125
b1110 +
b10100010000100110 1
b100110010100011100 0
b111010100101001100 /
b111111110001011100 .
1#
#556250
0#
#559375
b1111 +
b111010100101000010 1
b100000111001101000 0
b111010010110101000 /
b111111110001000100 .
1$
1#
#562500
0#
#565625
b10000 +
b11011011110101010 1
b11011010000010000 0
b111010000111101100 /
b111111110000101100 .
0$
1#
#568750
0#
#571875
b10001 +
b110110101110111010 1
b10101010111111100 0
b111001111000011000 /
b111111110000010100 .
1#
#575000
0#
#578125
b10010 +
b1100000110110110 1
b1111010000010100 0
b111001101000101100 /
b111111101111111100 .
1#
#581250
0#
#584375
b10011 +
b11011010111001010 1
b1000111001000000 0
b111001011000101000 /
b111111101111100100 .
1$
1#
#587500
0#
#590625
b10100 +
b100100010000001010 1
b10010001101000 0
b111001001000001100 /
b111111101111001100 .
0$
1#
#593750
0#
#596875
b10101 +
b100110100001110010 1
b111011011001110100 0
b111000110111011000 /
b111111101110110100 .
1#
#600000
0#
#603125
b10110 +
b100001111011100110 1
b110100010001001100 0
b111000100110001100 /
b111111101110011100 .
1#
#606250
0#
#609375
b10111 +
b10110001100110010 1
b101100110111011000 0
b111000010100101000 /
b111111101110000100 .
1$
1#
#612500
0#
#615625
b11000 +
b11000100001010 1
b100101001100000000 0
b111000000010101100 /
b111111101101101100 .
0$
1#
#618750
0#
#621875
b11001 +
b101000010000001010 1
b11101001110101100 0
b110111110000011000 /
b111111101101010100 .
1#
#625000
0#
#628125
b11010 +
b101011110110110 1
b10100111111000100 0
b110111011101101100 /
b111111101100111100 .
1#
#631250
0#
#634375
b11011 +
b11010011101111010 1
b1100011100110000 0
b110111001010101000 /
b111111101100100100 .
1$
1#
#637500
0#
#640625
b11100 +
b100110111010101010 1
b11100111011000 0
b110110110111001100 /
b111111101100001100 .
0$
1#
#643750
0#
#646875
b11101 +
b101010100010000010 1
b111010011110100100 0
b110110100011011000 /
b111111101011110100 .
1#
#650000
0#
#653125
b11110 +
b100101000000100110 1
b110001000001111100 0
b110110001111001100 /
b111111101011011100 .
1#
#656250
0#
#659375
b11111 +
b10110000010100010 1
b100111010001001000 0
b110101111010101000 /
b111111101011000100 .
1#
#662500
0#
#665625
b100000 +
b111101010011101010 1
b11101001011110000 0
b110101100101101100 /
b111111101010101100 .
1#
#668750
0#
#671875
b100001 +
06
b11010011111011010 1
b10010110001011100 0
b110101010000011000 /
b111111101010010100 .
1#
#675000
0#
#678125
b100010 +
b101101010000110110 1
b1000000001110100 0
b110100111010101100 /
b111111101001111100 .
b111111111111100111 ,
0"
1$
1#
#681250
0#
#684375
b100011 +
b110101010010101010 1
b111100111100100000 0
b110100100100101000 /
b111111101001100011 .
b111111111111100110 ,
0$
1#
#687500
0#
#690625
b100100 +
b110010001111001010 1
b110001100001001000 0
b110100001110001011 /
b111111101001001001 .
1#
#693750
0#
#696875
b100101 +
b100011110000010010 1
b100101101111010011 0
b110011110111010100 /
b111111101000101111 .
1#
#700000
0#
#703125
b100110 +
b1001011111100101 1
b11001100110100111 0
b110011100000000011 /
b111111101000010101 .
1#
#706250
0#
#709375
b100111 +
b100011000110001100 1
b1101000110101010 0
b110011001000011000 /
b111111100111111011 .
1#
#712500
0#
#715625
b101000 +
b110000001100110110 1
b1111000010 0
b110010110000010011 /
b111111100111100001 .
1#
#718750
0#
#721875
b101001 +
b110000011011111000 1
b110010111111010101 0
b110010010111110100 /
b111111100111000111 .
1#
#725000
0#
#728125
b101010 +
b100011011011001101 1
b100101010111001001 0
b110001111110111011 /
b111111100110101101 .
1#
#731250
0#
#734375
b101011 +
b1000110010010110 1
b10111010110000100 0
b110001100101101000 /
b111111100110010011 .
1#
#737500
0#
#740625
b101100 +
b100000001000011010 1
b1000111011101100 0
b110001001011111011 /
b111111100101111001 .
1#
#743750
0#
#746875
b101101 +
b101001000100000110 1
b111010000111100111 0
b110000110001110100 /
b111111100101011111 .
1$
1#
#750000
0#
#753125
b101110 +
b100011001011101101 1
b101010111001011011 0
b110000010111010011 /
b111111100101000101 .
0$
1#
#756250
0#
#759375
b101111 +
b1110000101001000 1
b11011010000101110 0
b101111111100011000 /
b111111100100101011 .
1#
#762500
0#
#765625
b110000 +
b101001010101110110 1
b1011001101000110 0
b101111100001000011 /
b111111100100010001 .
1#
#768750
0#
#771875
b110001 +
b110100100010111100 1
b111010101110001001 0
b101111000101010100 /
b111111100011110111 .
1#
#775000
0#
#778125
b110010 +
b101111010001000101 1
b101001110011011101 0
b101110101001001011 /
b111111100011011101 .
1#
#781250
0#
#784375
b110011 +
b11001000100100010 1
b11000011100101000 0
b101110001100101000 /
b111111100011000011 .
1#
#787500
0#
#790625
b110100 +
b110001100001001010 1
b110101001010000 0
b101101101111101011 /
b111111100010101001 .
1#
#793750
0#
#796875
b110101 +
b111000001010011010 1
b110100011000111011 0
b101101010010010100 /
b111111100010001111 .
1#
#800000
0#
#803125
b110110 +
b101100100011010101 1
b100001101011001111 0
b101100110100100011 /
b111111100001110101 .
1#
#806250
0#
#809375
b110111 +
b1110001110100100 1
b1110011111110010 0
b101100010110011000 /
b111111100001011011 .
1#
#812500
0#
#815625
b111000 +
b11100101110010110 1
b111010110110001010 0
b101011110111110011 /
b111111100001000001 .
1#
#818750
0#
#821875
b111001 +
b10111100100100000 1
b100110101101111101 0
b101011011000110100 /
b111111100000100111 .
1#
#825000
0#
#828125
b111010 +
b111110010010011101 1
b10010000110110001 0
b101010111001011011 /
b111111100000001101 .
1#
#831250
0#
#834375
b111011 +
b10000011001001110 1
b111101000000001100 0
b101010011001101000 /
b111111011111110011 .
1#
#837500
0#
#840625
b111100 +
b1101011001011010 1
b100111011001110100 0
b101001111001011011 /
b111111011111011001 .
1#
#843750
0#
#846875
b111101 +
b110100110011001110 1
b10001010011001111 0
b101001011000110100 /
b111111011110111111 .
1#
#850000
0#
#853125
b111110 +
b110000110011101 1
b111010101100000011 0
b101000110111110011 /
b111111011110100101 .
1#
#856250
0#
#859375
b111111 +
b110010100000 1
b100011100011110110 0
b101000010110011000 /
b111111011110001011 .
1#
#862500
0#
#865625
1>
16
b110010100000 =
b0 +
b100100010110010110 1
b1011111010001110 0
b100111110100100011 /
b111111011101110001 .
1#
#868750
0#
#871875
bx 3
bx 7
b101011101101100000 2
b110010100000 ;
1"
0>
b1 +
b110000010000100100 1
b110011101110110001 0
b100111010010010100 /
b111111011101010111 .
1#
#875000
0#
#878125
b10 +
b100011111111010101 1
b11011000001000101 0
b100110101111101011 /
b111111011100111101 .
1#
#881250
0#
#884375
b11 +
b111111000000011010 1
b1110000110000 0
b100110001100101000 /
b111111011100100011 .
1#
#887500
0#
#890625
b100 +
b110001001010 1
b100111111101011000 0
b100101101001001011 /
b111111011100001001 .
1#
#893750
0#
#896875
b101 +
b101000101110100010 1
b1101100110100011 0
b100101000101010100 /
b111111011011101111 .
1#
#900000
0#
#903125
b110 +
b110110010101000101 1
b110010101011110111 0
b100100100001000011 /
b111111011011010101 .
1#
#906250
0#
#909375
b111 +
b101001000000111100 1
b10111001100111010 0
b100011111100011000 /
b111111011010111011 .
1#
#912500
0#
#915625
b1000 +
b1101110110 1
b111011001001010010 0
b100011010111010011 /
b111111011010100001 .
1#
#918750
0#
#921875
b1001 +
b111011010111001000 1
b11110100000100101 0
b100010110001110100 /
b111111011010000111 .
1#
#925000
0#
#928125
b1010 +
b11001110111101101 1
b1010010011001 0
b100010001011111011 /
b111111011001101101 .
1#
#931250
0#
#934375
b1011 +
b11011001010000110 1
b100011011110010100 0
b100001100101101000 /
b111111011001010011 .
1#
#937500
0#
#940625
b1100 +
b111110101000011010 1
b101000011111100 0
b100000111110111011 /
b111111011000111001 .
1#
#943750
0#
#946875
b1101 +
b11101100010110 1
b100110000010110111 0
b100000010111110100 /
b111111011000011111 .
1#
#950000
0#
#953125
b1110 +
b101001101111001101 1
b110011010101011 0
b11111110000010011 /
b111111011000000101 .
1#
#956250
0#
#959375
b1111 +
b110000001001111000 1
b100110001010111110 0
b11111001000011000 /
b111111010111101011 .
1#
#962500
0#
#965625
b10000 +
b10110010100110110 1
b101010011010110 0
b11110100000000011 /
b111111010111010001 .
1#
#968750
0#
#971875
b10001 +
b11011101000001100 1
b100011110011011001 0
b11101110111010100 /
b111111010110110111 .
1#
#975000
0#
#978125
b10010 +
b111111011011100101 1
b1101010101101 0
b11101001110001011 /
b111111010110011101 .
1#
#981250
0#
#984375
b10011 +
b1000110010010 1
b11110111000111000 0
b11100100100101000 /
b111111010110000011 .
1#
#987500
0#
#990625
b10100 +
b11111111111001010 1
b111011011101100000 0
b11011111010101011 /
b111111010101101001 .
b111111111111100101 ,
1$
1#
#993750
0#
#996875
b10101 +
b11011011100101010 1
b10111011000001011 0
b11011010000010100 /
b111111010101001110 .
b111111111111100100 ,
0$
1#
#1000000
0#
#1003125
b10110 +
b110010110100110101 1
b110010101000011111 0
b11010100101100010 /
b111111010100110010 .
1#
#1006250
0#
#1009375
b10111 +
b100101011101010100 1
b1101001110000001 0
b11001111010010100 /
b111111010100010110 .
1#
#1012500
0#
#1015625
b11000 +
b110010101011010101 1
b100111001000010101 0
b11001001110101010 /
b111111010011111010 .
1#
#1018750
0#
#1021875
b11001 +
b11001110011101010 1
b10110111111 0
b11000100010100100 /
b111111010011011110 .
1#
#1025000
0#
#1028125
b11010 +
b11010001010101001 1
b11000111001100011 0
b10111110110000010 /
b111111010011000010 .
1#
#1031250
0#
#1034375
b11011 +
b110011000100001100 1
b110000101111100101 0
b10111001001000100 /
b111111010010100110 .
1#
#1037500
0#
#1040625
b11100 +
b100011110011110001 1
b111111000101001 0
b10110011011101010 /
b111111010010001010 .
b111111111111100011 ,
1$
1#
#1043750
0#
#1046875
b11101 +
b101011101100011010 1
b11110010100010011 0
b10101101101110100 /
b111111010001101101 .
b111111111111100010 ,
0$
1#
#1050000
0#
#1053125
b11110 +
b1010000000101101 1
b110100000010000111 0
b10100111111100001 /
b111111010001001111 .
1#
#1056250
0#
#1059375
b11111 +
b111110000010110100 1
b1001000001101000 0
b10100010000110000 /
b111111010000110001 .
1#
#1062500
0#
#1065625
b100000 +
b111000100011100 1
b11101010010011000 0
b10011100001100001 /
b111111010000010011 .
1#
#1068750
0#
#1071875
b100001 +
06
b100100010110110100 1
b110000110011111001 0
b10010110001110100 /
b111111001111110101 .
1$
1#
#1075000
0#
#1078125
b100010 +
b10101001010101101 1
b11100101101101 0
b10010000001101001 /
b111111001111010111 .
0"
0$
1#
#1081250
0#
#1084375
b100011 +
b11000110000011010 1
b10101100111010110 0
b10001010001000000 /
b111111001110111001 .
1#
#1087500
0#
#1090625
b100100 +
b101110010111110000 1
b100110111000010110 0
b10000011111111001 /
b111111001110011011 .
1#
#1093750
0#
#1096875
b100101 +
b10101010000000110 1
b110111011000001111 0
b1111101110010100 /
b111111001101111101 .
1$
1#
#1100000
0#
#1103125
b100110 +
b1100101000010101 1
b111000110100011 0
b1110111100010001 /
b111111001101011111 .
0$
1#
#1106250
0#
#1109375
b100111 +
b10011101110111000 1
b10110000010110100 0
b1110001001110000 /
b111111001101000001 .
1#
#1112500
0#
#1115625
b101000 +
b101001110001101100 1
b100100001100100100 0
b1101010110110001 /
b111111001100100011 .
1#
#1118750
0#
#1121875
b101001 +
b1101111110010000 1
b110001100011010101 0
b1100100011010100 /
b111111001100000101 .
1$
1#
#1125000
0#
#1128125
b101010 +
b111111100001100101 1
b111110000110101001 0
b1011101111011001 /
b111111001011100111 .
0$
1#
#1131250
0#
#1134375
b101011 +
b111101101000001110 1
b1001110110000010 0
b1010111011000000 /
b111111001011001001 .
1#
#1137500
0#
#1140625
b101100 +
b111011110010000 1
b10100110001000010 0
b1010000110001001 /
b111111001010101011 .
b111111111111100001 ,
1$
1#
#1143750
0#
#1146875
b101101 +
b11100001111010010 1
b11110110111001011 0
b1001010000110100 /
b111111001010001100 .
b111111111111100000 ,
0$
1#
#1150000
0#
#1153125
b101110 +
b111011000110011101 1
b101000000111111111 0
b1000011011000000 /
b111111001001101100 .
1#
#1156250
0#
#1159375
b101111 +
b100011001110011100 1
b110000100010111111 0
b111100100101100 /
b111111001001001100 .
1$
1#
#1162500
0#
#1165625
b110000 +
b10011110001011011 1
b111000000111101011 0
b110101101111000 /
b111111001000101100 .
0$
1#
#1168750
0#
#1171875
b110001 +
b1011111001000110 1
b111110110101100011 0
b101110110100100 /
b111111001000001100 .
1#
#1175000
0#
#1178125
b110010 +
b1010101110101001 1
b100101100000111 0
b100111110110000 /
b111111000111101100 .
b111111111111011111 ,
1$
1#
#1181250
0#
#1184375
b110011 +
b1111011010110000 1
b1001101010110111 0
b100000110011100 /
b111111000111001011 .
b111111111111011110 ,
0$
1#
#1187500
0#
#1190625
b110100 +
b11001000101100111 1
b1101110001010011 0
b11001101100111 /
b111111000110101001 .
1#
#1193750
0#
#1196875
b110101 +
b100110110110111010 1
b10000111110111010 0
b10010100010000 /
b111111000110000111 .
1$
1#
#1200000
0#
#1203125
b110110 +
b110111110101110100 1
b10011010011001010 0
b1011010010111 /
b111111000101100101 .
0$
1#
#1206250
0#
#1209375
b110111 +
b1011001000111110 1
b10100101101100001 0
b11111111100 /
b111111000101000011 .
1$
1#
#1212500
0#
#1215625
b111000 +
b11111110110011111 1
b10101001101011101 0
b111111100100111111 /
b111111000100100001 .
0$
1#
#1218750
0#
#1221875
b111001 +
b110101000011111100 1
b10100110010011100 0
b111110101001100000 /
b111111000011111111 .
1#
#1225000
0#
#1228125
b111010 +
b1001110110011000 1
b10011011011111100 0
b111101101101011111 /
b111111000011011101 .
b111111111111011101 ,
1$
1#
#1231250
0#
#1234375
b111011 +
b11101010010010100 1
b10001001001011011 0
b111100110000111100 /
b111111000010111010 .
b111111111111011100 ,
0$
1#
#1237500
0#
#1240625
b111100 +
b101110011011101111 1
b1101111010010111 0
b111011110011110110 /
b111111000010010110 .
b111111111111011011 ,
1$
1#
#1243750
0#
#1246875
b111101 +
b111100010110000110 1
b1001101110001101 0
b111010110110001100 /
b111111000001110001 .
b111111111111011010 ,
0$
1#
#1250000
0#
#1253125
b111110 +
b110000100010011 1
b100100100011001 0
b111001110111111101 /
b111111000001001011 .
b111111111111011001 ,
1$
1#
#1256250
0#
#1259375
b111111 +
b1010101000101100 1
b111110011100010110 0
b111000111001001000 /
b111111000000100100 .
b111111111111011000 ,
0$
1#
#1262500
0#
#1265625
1>
16
b1010101000101100 =
b0 +
b1001000101000010 1
b110111010101011110 0
b110111111001101100 /
b111110111111111100 .
b111111111111010111 ,
1$
1#
#1268750
0#
#1271875
bx 4
bx 8
b101011101101100000 7
b1001110110001100 2
b1010101000101100 ;
1"
0>
b1 +
b11010100000 1
b101111001111001010 0
b110110111001101000 /
b111110111111010011 .
b111111111111010110 ,
0$
1#
#1275000
0#
#1278125
b10 +
b101111101001101010 1
b100110001000110010 0
b110101111000111011 /
b111110111110101001 .
b111111111111010101 ,
1$
1#
#1281250
0#
#1284375
b11 +
b10101110010011100 1
b11100000001101101 0
b110100110111100100 /
b111110111101111110 .
b111111111111010100 ,
0$
1#
